Metadata-Version: 2.1
Name: avro-preprocessor
Version: 0.9.1
Summary: A preprocessor for Avro Schemata
Home-page: https://gitlab.com/Jaumo/avro-preprocessor
Author: Jaumo GmbH
Author-email: nicola.bova@jaumo.com
License: Apache2
Keywords: avro,preprocessor,schema,schemas,schemata
License-File: COPYING
Requires-Dist: networkx (>=2.8.7)
Requires-Dist: pygments (>=2.13.0)
Requires-Dist: requests (>=2.28.1)
Requires-Dist: ruamel.yaml (>=0.17.21)
Requires-Dist: ruamel.yaml.clib (>=0.2.6)
Requires-Dist: json5 (>=0.9.21)
